setup.cfg
setup.py
dist_alx/__init__.py
dist_alx/database.py
python_database.egg-info/PKG-INFO
python_database.egg-info/SOURCES.txt
python_database.egg-info/dependency_links.txt
python_database.egg-info/not-zip-safe
python_database.egg-info/top_level.txt