Metadata-Version: 2.1
Name: python-database
Version: 0.0
Summary: Python Database WITH NOT SQL!
Home-page: UNKNOWN
Author-email: timafeusivanov@gmail.com
License: UNKNOWN
Platform: UNKNOWN
